README.txt
bootstrap.py
buildout.cfg
setup.cfg
setup.py
Products/__init__.py
Products.DCWorkflowGraph.egg-info/PKG-INFO
Products.DCWorkflowGraph.egg-info/SOURCES.txt
Products.DCWorkflowGraph.egg-info/dependency_links.txt
Products.DCWorkflowGraph.egg-info/entry_points.txt
Products.DCWorkflowGraph.egg-info/namespace_packages.txt
Products.DCWorkflowGraph.egg-info/not-zip-safe
Products.DCWorkflowGraph.egg-info/paster_plugins.txt
Products.DCWorkflowGraph.egg-info/requires.txt
Products.DCWorkflowGraph.egg-info/top_level.txt
Products/DCWorkflowGraph/DCWorkflowGraph.py
Products/DCWorkflowGraph/DCWorkflowGraph_Rank.py
Products/DCWorkflowGraph/__init__.py
Products/DCWorkflowGraph/config.py
Products/DCWorkflowGraph/install.txt
Products/DCWorkflowGraph/refresh.txt
Products/DCWorkflowGraph/todo.txt
Products/DCWorkflowGraph/version.txt
Products/DCWorkflowGraph/i18n/DCWorkflowGraph-es.po
Products/DCWorkflowGraph/i18n/DCWorkflowGraph.pot
Products/DCWorkflowGraph/www/manage_workflowGraph.zpt
docs/HISTORY.txt
docs/INSTALL.txt
docs/LICENSE.GPL
docs/LICENSE.txt