Metadata-Version: 1.0
Name: Products.DCWorkflowGraph
Version: 0.4.1
Summary: DCWorkflowGraph is a DCWorkflow graphic viewer now. It uses Graphviz.
Home-page: http://svn.plone.org/svn/collective/Products.DCWorkflowGraph/
Author: Author: panjunyong (panjy at zopen.cn, from ZOpen)
Author-email: panjy at zopen.cn
License: ZPL
Platform: UNKNOWN
Classifier: Framework :: Plone
Classifier: Programming Language :: Python
Classifier: Topic :: Software Development :: Libraries :: Python Modules
